adlerpy/__init__.py
adlerpy/adler_routines.py
adlerpy/adler_sm.py
adlerpy-0.1.3.dist-info/METADATA
adlerpy-0.1.3.dist-info/WHEEL
adlerpy-0.1.3.dist-info/top_level.txt
adlerpy-0.1.3.dist-info/RECORD
