Metadata-Version: 2.1
Name: adlerpy
Version: 0.1.3
Summary: A code to compute the Adler function
Home-page: https://github.com/rodofer2020/adlerpy.git
Author: Rodolfo F
Author-email: rferro@he-uni.mainz.de
License: BSD 2-clause
Platform: UNKNOWN
Classifier: Development Status :: 1 - Planning
Classifier: Intended Audience :: Science/Research
Classifier: License :: OSI Approved :: BSD License
Classifier: Operating System :: POSIX :: Linux
Classifier: Programming Language :: Python :: 2
Classifier: Programming Language :: Python :: 2.7
Classifier: Programming Language :: Python :: 3
Classifier: Programming Language :: Python :: 3.4
Classifier: Programming Language :: Python :: 3.5
Requires-Dist: numpy
Requires-Dist: rundec
Requires-Dist: mpmath
Requires-Dist: scipy
